clay/__init__.py
clay/celery.py
clay/config.py
clay/database.py
clay/docs.py
clay/http.py
clay/logger.py
clay/mail.py
clay/sentry.py
clay/server.py
clay/stats.py
clay/wsgi.py
clay_flask-2.1.8.dist-info/DESCRIPTION.rst
clay_flask-2.1.8.dist-info/METADATA
clay_flask-2.1.8.dist-info/RECORD
clay_flask-2.1.8.dist-info/WHEEL
clay_flask-2.1.8.dist-info/entry_points.txt
clay_flask-2.1.8.dist-info/metadata.json
clay_flask-2.1.8.dist-info/top_level.txt
