Metadata-Version: 2.0
Name: clay-flask
Version: 2.1.8
Summary: Clay is a framework for building RESTful backend services using best practices.
Home-page: UNKNOWN
Author: Jeremy Grosser
Author-email: jeremy@uber.com
License: UNKNOWN
Platform: UNKNOWN
Requires-Dist: flask
